{"mean":{"confidence_interval":{"confidence_level":0.95,"lower_bound":273224.98064709676,"upper_bound":274700.0924049046},"point_estimate":273905.22844147007,"standard_error":376.2344585146616},"median":{"confidence_interval":{"confidence_level":0.95,"lower_bound":272994.05323223036,"upper_bound":274255.25},"point_estimate":273582.85113636364,"standard_error":328.2710553680853},"median_abs_dev":{"confidence_interval":{"confidence_level":0.95,"lower_bound":1849.8448409085897,"upper_bound":2959.874087703269},"point_estimate":2269.888237710542,"standard_error":287.97786507889435},"slope":{"confidence_interval":{"confidence_level":0.95,"lower_bound":273774.8258496788,"upper_bound":276369.45894287614},"point_estimate":274931.1847103591,"standard_error":666.247131956361},"std_dev":{"confidence_interval":{"confidence_level":0.95,"lower_bound":2311.128148420085,"upper_bound":5374.4762446375835},"point_estimate":3781.314321854452,"standard_error":849.78555760027}}